ciris/__init__.py
ciris-1.0.0.dist-info/LICENSE.md
ciris-1.0.0.dist-info/METADATA
ciris-1.0.0.dist-info/WHEEL
ciris-1.0.0.dist-info/top_level.txt
ciris-1.0.0.dist-info/RECORD
