Metadata-Version: 2.1
Name: ciris
Version: 1.0.0
Summary: A lightweight Python library that makes working with color easy
Author-email: nickythelion <nickythelionfurry@yandex.ru>
Project-URL: Homepage, https://github.com/nickythelion/iris
Classifier: Development Status :: 5 - Production/Stable
Classifier: Intended Audience :: Developers
Classifier: Intended Audience :: Other Audience
Classifier: License :: OSI Approved :: MIT License
Classifier: Natural Language :: English
Classifier: Operating System :: OS Independent
Classifier: Programming Language :: Python
Classifier: Programming Language :: Python :: 3
Classifier: Programming Language :: Python :: 3.8
Classifier: Programming Language :: Python :: 3.9
Classifier: Programming Language :: Python :: 3.10
Classifier: Programming Language :: Python :: 3.11
Classifier: Topic :: Utilities
Classifier: Typing :: Typed
Requires-Python: >=3.8
License-File: LICENSE.md
Provides-Extra: dev
Requires-Dist: pytest (~=7.2.0) ; extra == 'dev'
Requires-Dist: typing-extensions (~=4.4.0) ; extra == 'dev'
Requires-Dist: black (~=22.10.0) ; extra == 'dev'
